assertfunction/__init__.py
assertfunction/core/__init__.py
assertfunction/tests/__init__.py
assertfunction/tests/test_0.py
assertfunction-1.0.3.dist-info/LICENSE.txt
assertfunction-1.0.3.dist-info/METADATA
assertfunction-1.0.3.dist-info/WHEEL
assertfunction-1.0.3.dist-info/top_level.txt
assertfunction-1.0.3.dist-info/RECORD
