Metadata-Version: 2.2
Name: assertfunction
Version: 1.0.3
Summary: This project provides a function that binds the assert command.
Author-email: Johannes <johannes-programming@mailfence.com>
License: The MIT License (MIT)
Project-URL: Download, https://pypi.org/project/assertfunction/#files
Project-URL: Index, https://pypi.org/project/assertfunction/
Project-URL: Source, https://github.com/johannes-programming/assertfunction/
Project-URL: Website, https://assertfunction.johannes-programming.online/
Classifier: Development Status :: 5 - Production/Stable
Classifier: Intended Audience :: Developers
Classifier: License :: OSI Approved :: MIT License
Classifier: Natural Language :: English
Classifier: Operating System :: OS Independent
Classifier: Programming Language :: Python
Classifier: Programming Language :: Python :: 3
Classifier: Programming Language :: Python :: 3 :: Only
Classifier: Typing :: Typed
Requires-Python: >=3.8
License-File: LICENSE.txt
Requires-Dist: overloadable>=1.0.9
